eo_man/__init__.py
eo_man/__main__.py
eo_man/controller/__init__.py
eo_man/controller/app_bus.py
eo_man/controller/bus_burst_tester.py
eo_man/controller/enocean_logger.py
eo_man/controller/gateway_registry.py
eo_man/controller/lan_service_detector.py
eo_man/controller/network_gateway_detector.py
eo_man/controller/serial_controller.py
eo_man/controller/serial_port_detector.py
eo_man/data/__init__.py
eo_man/data/app_info.py
eo_man/data/application_data.py
eo_man/data/const.py
eo_man/data/data_helper.py
eo_man/data/data_manager.py
eo_man/data/device.py
eo_man/data/filter.py
eo_man/data/ha_config_generator.py
eo_man/data/message_history.py
eo_man/data/pct14_data_manager.py
eo_man/data/recorded_message.py
eo_man/data/homeassistant/__init__.py
eo_man/data/homeassistant/const.py
eo_man/icons/Breathe-about.png
eo_man/icons/EUL_device.png
eo_man/icons/Faenza-system-search.bmp
eo_man/icons/Faenza-system-search.ico
eo_man/icons/Faenza-system-search.png
eo_man/icons/Gnome-help-faq.png
eo_man/icons/Home_Assistant_Logo.png
eo_man/icons/Oxygen480-actions-document-save-as.png
eo_man/icons/Oxygen480-actions-document-save.png
eo_man/icons/Oxygen480-actions-edit-clear.png
eo_man/icons/Oxygen480-actions-help.png
eo_man/icons/Oxygen480-status-folder-open.png
eo_man/icons/Software-update-available.png
eo_man/icons/__init__.py
eo_man/icons/blank.png
eo_man/icons/export_icon.png
eo_man/icons/fam-usb.png
eo_man/icons/fam-usb2.png
eo_man/icons/fam14.jpg
eo_man/icons/fam14.png
eo_man/icons/fgw14-usb.png
eo_man/icons/ftd14.png
eo_man/icons/github_icon.png
eo_man/icons/image_gallary.py
eo_man/icons/mail-forward.png
eo_man/icons/mail-send-receive.png
eo_man/icons/mgw_piotek.png
eo_man/icons/paypal_icon.png
eo_man/icons/paypal_me_badge.png
eo_man/icons/pct14.png
eo_man/icons/usb300.png
eo_man/icons/wireless-network-bw.png
eo_man/icons/wireless-network-colored.png
eo_man/icons/wireless.png
eo_man/view/__init__.py
eo_man/view/about_window.py
eo_man/view/checklistcombobox.py
eo_man-0.1.54.dist-info/licenses/LICENSE
eo_man-0.1.54.dist-info/METADATA
eo_man-0.1.54.dist-info/WHEEL
eo_man-0.1.54.dist-info/top_level.txt
eo_man-0.1.54.dist-info/RECORD
