Metadata-Version: 2.4
Name: eo_man
Version: 0.1.54
Summary: Tool to managed EnOcean Devices and to generate Home Assistant Configuration.
Author: Philipp Grimm
License: MIT
Project-URL: Homepage, https://github.com/grimmpp/enocean-device-manager
Project-URL: Documentation, https://github.com/grimmpp/enocean-device-manager/tree/main/docs/getting-started
Project-URL: Repository, https://github.com/grimmpp/enocean-device-manager.git
Keywords: enocean,device manager,eltako
Classifier: Programming Language :: Python :: 3
Classifier: License :: OSI Approved :: MIT License
Classifier: Operating System :: OS Independent
Requires-Python: >=3.12
License-File: LICENSE
Requires-Dist: aiocoap==0.4.7
Requires-Dist: eltako14bus==0.0.79
Requires-Dist: numpy
Requires-Dist: pillow>=11
Requires-Dist: pyserial==3.5
Requires-Dist: pyserial-asyncio==0.6
Requires-Dist: PyYAML==6.0.1
Requires-Dist: StrEnum==0.4.15
Requires-Dist: termcolor==2.4.0
Requires-Dist: tkinterhtml==0.7
Requires-Dist: requests==2.31.0
Requires-Dist: enocean==0.60.1
Requires-Dist: esp2_gateway_adapter==0.2.20
Requires-Dist: zeroconf
Requires-Dist: tkScrolledFrame==1.0.4
Requires-Dist: xmltodict
Requires-Dist: tomli
Dynamic: license-file
